<annotation>
	<folder>New folder</folder>
	<filename>tehari 29.jpg</filename>
	<path>C:\Users\Wheatstone\Desktop\New folder\tehari 29.jpg</path>
	<source>
		<database>Unknown</database>
	</source>
	<size>
		<width>960</width>
		<height>881</height>
		<depth>3</depth>
	</size>
	<segmented>0</segmented>
	<object>
		<name>tehari</name>
		<pose>Unspecified</pose>
		<truncated>0</truncated>
		<difficult>0</difficult>
		<bndbox>
			<xmin>186</xmin>
			<ymin>150</ymin>
			<xmax>794</xmax>
			<ymax>740</ymax>
		</bndbox>
	</object>
</annotation>
